wrc_rallydj/__init__.py
wrc_rallydj/livetiming_api.py
wrc_rallydj-0.0.2.dist-info/LICENSE
wrc_rallydj-0.0.2.dist-info/METADATA
wrc_rallydj-0.0.2.dist-info/WHEEL
wrc_rallydj-0.0.2.dist-info/top_level.txt
wrc_rallydj-0.0.2.dist-info/RECORD
