Metadata-Version: 2.2
Name: wrc_rallydj
Version: 0.0.2
Summary: RallyDatajunkie package for making requests to WRC live timing, results and data APIs.
Home-page: https://github.com/RallyDataJunkie/wrc-shinylive
Author: Tony Hirst
Author-email: tony.hirst@gmnail.com
Classifier: Programming Language :: Python :: 3
Classifier: License :: OSI Approved :: MIT License
Classifier: Operating System :: OS Independent
License-File: LICENSE
Requires-Dist: numpy
Requires-Dist: pandas
Requires-Dist: sqlite_utils
Requires-Dist: jupyterlite_simple_cors_proxy
Dynamic: author
Dynamic: author-email
Dynamic: classifier
Dynamic: description
Dynamic: description-content-type
Dynamic: home-page
Dynamic: requires-dist
Dynamic: summary
